coze_mcp_server/__init__.py
coze_mcp_server/__main__.py
coze_mcp_server/server.py
coze_mcp_server-0.0.4.dist-info/METADATA
coze_mcp_server-0.0.4.dist-info/WHEEL
coze_mcp_server-0.0.4.dist-info/entry_points.txt
coze_mcp_server-0.0.4.dist-info/licenses/LICENSE
coze_mcp_server-0.0.4.dist-info/RECORD
