Metadata-Version: 2.4
Name: coze-mcp-server
Version: 0.0.4
Summary: MCP Server for Coze(coze.com/coze.cn)
Author-email: chyroc <chyroc@bytedance.com>
License: MIT
License-File: LICENSE
Keywords: coze,llm,mcp
Requires-Python: <4.0,>=3.10
Requires-Dist: cozepy>=0.13.0
Requires-Dist: mcp[cli]>=1.5.0
Requires-Dist: pydantic>=2.0.0
